snapenv_core/__init__.py
snapenv_core/py.typed
snapenv_core/settings/__init__.py
snapenv_core/settings/manager.py
snapenv_core-0.3.0.dist-info/METADATA
snapenv_core-0.3.0.dist-info/WHEEL
snapenv_core-0.3.0.dist-info/RECORD
