Metadata-Version: 2.3
Name: snapenv-core
Version: 0.3.0
Summary: Awesome snapenv_core created by snapenv
Author: Abner G Jacobsen
Author-email: abner@apoana.com.br
Requires-Python: >=3.11,<3.14
Classifier: Programming Language :: Python :: 3
Classifier: Programming Language :: Python :: 3.11
Classifier: Programming Language :: Python :: 3.12
Classifier: Programming Language :: Python :: 3.13
Requires-Dist: pydantic (>=2.8.2,<3.0.0)
Requires-Dist: pydantic-settings (>=2.4.0,<3.0.0)
Project-URL: Repository, https://github.com/snapenv/snapenv-core
